igo/__init__.py
igo/dictionary.py
igo/dictreader.py
igo/parse.py
igo/tagger.py
igo/trie.py
igo/ipadic/char.category
igo/ipadic/code2category
igo/ipadic/matrix.bin
igo/ipadic/word.ary.idx
igo/ipadic/word.dat
igo/ipadic/word.inf
igo/ipadic/word2id
igo_python-1.0.0.dist-info/METADATA
igo_python-1.0.0.dist-info/RECORD
igo_python-1.0.0.dist-info/WHEEL
igo_python-1.0.0.dist-info/entry_points.txt
igo_python-1.0.0.dist-info/top_level.txt
